{
	"1": [
		{ "id": 221, "name": "Matematika", "isElective": false, "ects": 7 },
		{ "id": 222, "name": "Elektrotehnika", "isElective": false, "ects": 6 },
		{ "id": 223, "name": "Uvod u organizaciju digitalnih računala", "isElective": false, "ects": 5 },
		{ "id": 224, "name": "Programiranje 1", "isElective": false, "ects": 10 },
		{ "id": 225, "name": "Engleski jezik 1", "isElective": false, "ects": 2 }
	],
	"2": [
		{ "id": 226, "name": "Primijenjena matematika", "isElective": false, "ects": 5 },
		{ "id": 227, "name": "Osnove elektronike", "isElective": false, "ects": 5 },
		{ "id": 228, "name": "Digitalna tehnika", "isElective": false, "ects": 7 },
		{ "id": 229, "name": "Programiranje 2", "isElective": false, "ects": 10 },
		{ "id": 230, "name": "Engleski jezik 2", "isElective": false, "ects": 3 }
	],
	"3": [
		{ "id": 231, "name": "Uvod u poduzetništvo", "isElective": false, "ects": 4 },
		{ "id": 232, "name": "Arhitektura digitalnih računala", "isElective": false, "ects": 6 },
		{ "id": 233, "name": "Baze podataka", "isElective": false, "ects": 5 },
		{ "id": 234, "name": "Algoritmi i strukture podataka", "isElective": false, "ects": 5 },
		{ "id": 235, "name": "Programiranje za Unix", "isElective": false, "ects": 5 },
		{ "id": 236, "name": "Programiranje za Internet", "isElective": false, "ects": 5 }
	],
	"4": [
		{ "id": 237, "name": "Računalne mreže", "isElective": false, "ects": 5 },
		{ "id": 238, "name": "Operacijski sustavi", "isElective": false, "ects": 7 },
		{ "id": 239, "name": "Objektno orijentirano programiranje", "isElective": false, "ects": 7 },
		{ "id": 240, "name": "Programiranje u Javi", "isElective": false, "ects": 6 },
		{ "id": 240, "name": "Multimedijske mreže i sustavi", "isElective": false, "ects": 5 }
	],
	"5": [
		{ "id": 241, "name": "Programsko inženjerstvo", "isElective": false, "ects": 5 },
		{ "id": 242, "name": "Uvod u distribuirane informacijske sustave", "isElective": false, "ects": 5 },
		{ "id": 243, "name": "Arhitektura osobnih računala", "isElective": true, "ects": 5 },
		{ "id": 244, "name": "Programiranje za Windows", "isElective": true, "ects": 5 },
		{ "id": 245, "name": "Baze podataka 2", "isElective": true, "ects": 5 },
		{ "id": 246, "name": "Sigurnost računala i podataka", "isElective": true, "ects": 5 },
		{ "id": 247, "name": "Projektiranje i korištenje računalnih mreža", "isElective": true, "ects": 5 },
		{ "id": 248, "name": "Napredne web tehnologije", "isElective": true, "ects": 5 },
		{ "id": 249, "name": "Upravljanje poslovnim procesima", "isElective": true, "ects": 5 }
	],
	"6": [
		{ "id": 250, "name": "Projektiranje informacijskih sustava", "isElective": false, "ects": 5 },
		{ "id": 251, "name": "Stručna praksa", "isElective": false, "ects": 10 },
		{ "id": 252, "name": "Završni rad", "isElective": false, "ects": 10 },
		{ "id": 253, "name": "Mikrokontrolerom upravljani mobilni roboti", "isElective": true, "ects": 5 },
		{ "id": 254, "name": "Mobilne komunikacijske mreže", "isElective": true, "ects": 5 },
		{ "id": 255, "name": "Osnove programiranja 3D računalnih igara", "isElective": true, "ects": 5 },
		{ "id": 256, "name": "Programiranje za android", "isElective": true, "ects": 5 }
	]
}
